Metadata-Version: 2.1
Name: word-identifiers
Version: 1.0.0
Summary: Provides a bijection between numbers and lists of english words.
Home-page: https://github.com/kavigupta/word-identifiers
Author: Kavi Gupta
Author-email: word_identifiers@kavigupta.org
License: UNKNOWN
Platform: UNKNOWN
Classifier: Programming Language :: Python :: 3.5
Classifier: Programming Language :: Python :: 3.6
Classifier: Programming Language :: Python :: 3.7
Classifier: Programming Language :: Python :: 3.8
Classifier: Operating System :: OS Independent
Requires-Python: >=3.5
